PathFinderlib/__init__.py
tests/__init__.py
PathFinderlib-0.1.0.dist-info/LICENSE.txt
PathFinderlib-0.1.0.dist-info/METADATA
PathFinderlib-0.1.0.dist-info/WHEEL
PathFinderlib-0.1.0.dist-info/top_level.txt
PathFinderlib-0.1.0.dist-info/RECORD
