Metadata-Version: 2.1
Name: PathFinderlib
Version: 0.1.0
Summary: A package to implement Pathfinding into your games
Home-page: UNKNOWN
Author: Me
License: MIT
Platform: UNKNOWN
License-File: LICENSE.txt
